PlatformConnectors/PackageMaker.py
PlatformConnectors/PlatformConnectors.py
PlatformConnectors/PlatformHelpers.py
PlatformConnectors/SecretType.py
PlatformConnectors/__init__.py
buzzerboy_platform_connectors-0.23.7.dist-info/licenses/LICENSE
buzzerboy_platform_connectors-0.23.7.dist-info/METADATA
buzzerboy_platform_connectors-0.23.7.dist-info/WHEEL
buzzerboy_platform_connectors-0.23.7.dist-info/top_level.txt
buzzerboy_platform_connectors-0.23.7.dist-info/RECORD
