Metadata-Version: 2.4
Name: buzzerboy-platform-connectors
Version: 0.23.7
Summary: Buzzerboy Platform Connectors parses integration json into useable django keys
Home-page: https://www.buzzerboy.com/
Author: Buzzerboy Inc
Author-email: Buzzerboy Inc <info@buzzerboy.com>
License: Copyright (c) 2024 Buzzerboy Inc. Canada. All Rights Reserved.
Project-URL: Homepage, https://www.buzzerboy.com/
Project-URL: Issues, https://dev.azure.com/buzzerboyinc/buzzerboy
Classifier: Programming Language :: Python :: 3
Classifier: License :: OSI Approved :: MIT License
Classifier: Operating System :: OS Independent
Requires-Python: >=3.8
License-File: LICENSE
Requires-Dist: toml
Requires-Dist: django
Requires-Dist: python-decouple
Dynamic: author
Dynamic: home-page
Dynamic: license-file
Dynamic: requires-dist
Dynamic: requires-python
